flocklab/__init__.py
flocklab/__main__.py
flocklab/_version.py
flocklab/flocklab.py
flocklab/visualization.py
flocklab/xmlconfig.py
flocklab_tools-0.2.9.dist-info/LICENSE
flocklab_tools-0.2.9.dist-info/METADATA
flocklab_tools-0.2.9.dist-info/WHEEL
flocklab_tools-0.2.9.dist-info/entry_points.txt
flocklab_tools-0.2.9.dist-info/top_level.txt
flocklab_tools-0.2.9.dist-info/RECORD
