Metadata-Version: 2.1
Name: flocklab-tools
Version: 0.2.9
Summary: Python support for using the FlockLab 2 testbed (flocklab CLI, creating flocklab xml, visualization).
Home-page: https://flocklab.ethz.ch/
Author: Computer Engineering Group, ETH Zurich
Author-email: rtrueb@ethz.ch
License: BSD 3-Clause
Platform: UNKNOWN
Classifier: Programming Language :: Python :: 3
Classifier: License :: OSI Approved :: MIT License
Classifier: Operating System :: OS Independent
Requires-Python: >=3.6
License-File: LICENSE
Requires-Dist: setuptools (>=50.3.0)
Requires-Dist: numpy (<2.0,>=1.19.1)
Requires-Dist: pandas (<2.0,>=1.1.1)
Requires-Dist: bokeh (<3.0,>=2.1.1)
Requires-Dist: requests (<3.0,>=2.22.0)
Requires-Dist: appdirs (<1.5,>=1.4.3)
Requires-Dist: rocketlogger (<3.0,>=2.0)
Requires-Dist: pyelftools (<1.0,>=0.26)
